{"info":{"year":"2026","version":"dataset","description":"Exported from roboflow.com","contributor":"","url":"https://public.roboflow.com/object-detection/undefined","date_created":"2026-03-08T19:21:40+00:00"},"licenses":[{"id":1,"url":"https://creativecommons.org/licenses/by/4.0/","name":"CC BY 4.0"}],"categories":[{"id":0,"name":"objects","supercategory":"none"},{"id":1,"name":"teacher sitting","supercategory":"objects"}],"images":[{"id":0,"license":1,"file_name":"0003_jpeg.rf.b6CkdZ3qFDEOXYPmDiab.jpeg","height":1470,"width":1024,"date_captured":"2026-03-08T19:21:40+00:00","extra":{"user_tags":["Jesus-Christ"],"name":"0003.jpeg"}}],"annotations":[{"id":1,"image_id":0,"category_id":1,"bbox":[396,171,"231.2857","337.5918"],"area":78080.156,"segmentation":[],"iscrowd":0,"keypoints":[500.857,225.188,2,517.429,223.475,2,510.571,233.754,2,488.857,225.188,2,472.857,258.311,2,524.857,226.33,2,534,262.309,2,454,314.278,2,545.429,294.29,2,471.714,337.693,2,528.286,335.979,2,498.571,294.861,2,558.571,333.695,2,467.143,393.089,2,527.714,391.375,2,467.714,470.186,2,525.429,469.615,2]}]}